{"frames":[{"x":3,"y":10,"w":118,"h":109},{"x":127,"y":21,"w":118,"h":97},{"x":245,"y":19,"w":111,"h":99},{"x":397,"y":20,"w":159,"h":100},{"x":556,"y":21,"w":113,"h":97},{"x":662,"y":20,"w":108,"h":99},{"x":775,"y":21,"w":106,"h":97},{"x":889,"y":24,"w":116,"h":93},{"x":289,"y":141,"w":125,"h":75},{"x":428,"y":130,"w":130,"h":86},{"x":579,"y":145,"w":132,"h":71},{"x":12,"y":326,"w":180,"h":102},{"x":8,"y":470,"w":74,"h":94},{"x":88,"y":470,"w":113,"h":94},{"x":196,"y":459,"w":131,"h":105},{"x":576,"y":456,"w":108,"h":108},{"x":329,"y":476,"w":90,"h":86},{"x":406,"y":478,"w":70,"h":83},{"x":490,"y":476,"w":72,"h":86},{"x":700,"y":476,"w":152,"h":88}]}