[{"x":96,"y":43,"w":48,"h":81,"area":2402,"i":0},{"x":176,"y":43,"w":47,"h":81,"area":2365,"i":1},{"x":252,"y":43,"w":48,"h":81,"area":2412,"i":2},{"x":404,"y":44,"w":49,"h":80,"area":2472,"i":3},{"x":488,"y":44,"w":48,"h":80,"area":2471,"i":4},{"x":571,"y":44,"w":48,"h":80,"area":2466,"i":5},{"x":658,"y":44,"w":52,"h":80,"area":2478,"i":6},{"x":748,"y":44,"w":49,"h":80,"area":2359,"i":7},{"x":838,"y":44,"w":47,"h":80,"area":2340,"i":8},{"x":83,"y":154,"w":79,"h":74,"area":2571,"i":9},{"x":220,"y":156,"w":71,"h":72,"area":2538,"i":10},{"x":356,"y":155,"w":84,"h":73,"area":3237,"i":11},{"x":459,"y":158,"w":78,"h":70,"area":2197,"i":12},{"x":568,"y":159,"w":55,"h":66,"area":2090,"i":13},{"x":676,"y":162,"w":76,"h":65,"area":2240,"i":14},{"x":802,"y":158,"w":118,"h":70,"area":3562,"i":15},{"x":83,"y":264,"w":64,"h":72,"area":2476,"i":16},{"x":182,"y":262,"w":63,"h":73,"area":2539,"i":17},{"x":273,"y":264,"w":59,"h":71,"area":2536,"i":18},{"x":365,"y":264,"w":60,"h":71,"area":2515,"i":19}]